mu_pipelines_execute_spark/__init__.py
mu_pipelines_execute_spark/context/__init__.py
mu_pipelines_execute_spark/context/spark_context.py
mu_pipelines_execute_spark/ingest_csv/__init__.py
mu_pipelines_execute_spark/ingest_csv/ingest_csv.py
mu_pipelines_execute_spark/load_csv/__init__.py
mu_pipelines_execute_spark/load_csv/load_csv.py
mu_pipelines_execute_spark/transform_sql/__init__.py
mu_pipelines_execute_spark/transform_sql/transform_sql.py
mu_pipelines_execute_spark-0.4.0.dist-info/entry_points.txt
mu_pipelines_execute_spark-0.4.0.dist-info/licenses/LICENSE
mu_pipelines_execute_spark-0.4.0.dist-info/WHEEL
mu_pipelines_execute_spark-0.4.0.dist-info/METADATA
mu_pipelines_execute_spark-0.4.0.dist-info/RECORD
